flicky/__init__.py
flicky/builder/__init__.py
flicky/builder/compiler.py
flicky/cli/__init__.py
flicky/cli/main.py
flicky/core/__init__.py
flicky/core/server.py
flicky/core/widget.py
flicky/types/__init__.py
flicky/types/schema.py
flicky-1.0.1.dist-info/licenses/LICENSE
flicky-1.0.1.dist-info/METADATA
flicky-1.0.1.dist-info/WHEEL
flicky-1.0.1.dist-info/entry_points.txt
flicky-1.0.1.dist-info/top_level.txt
flicky-1.0.1.dist-info/RECORD
