Metadata-Version: 2.4
Name: flicky
Version: 1.0.1
Summary: A zero-boilerplate framework for building interactive ChatGPT widgets
Home-page: https://github.com/flick-framework/flick
Author: Flick Team
Author-email: Flick Team <hello@flick.dev>
License: MIT
Project-URL: Homepage, https://flick.dev
Project-URL: Documentation, https://flick.dev/docs
Project-URL: Repository, https://github.com/flick-framework/flick
Project-URL: Bug Reports, https://github.com/flick-framework/flick/issues
Keywords: chatgpt,widgets,mcp,framework,react
Classifier: Development Status :: 4 - Beta
Classifier: Intended Audience :: Developers
Classifier: Topic :: Software Development :: Libraries :: Application Frameworks
Classifier: License :: OSI Approved :: MIT License
Classifier: Programming Language :: Python :: 3
Classifier: Programming Language :: Python :: 3.11
Classifier: Programming Language :: Python :: 3.12
Requires-Python: >=3.11
License-File: LICENSE
Requires-Dist: fastmcp>=0.1.0
Requires-Dist: pydantic>=2.0.0
Requires-Dist: uvicorn>=0.20.0
Requires-Dist: click>=8.0.0
Requires-Dist: rich>=13.0.0
Provides-Extra: dev
Requires-Dist: pytest>=7.0.0; extra == "dev"
Requires-Dist: pytest-asyncio>=0.21.0; extra == "dev"
Requires-Dist: black>=23.0.0; extra == "dev"
Requires-Dist: ruff>=0.1.0; extra == "dev"
Dynamic: author
Dynamic: home-page
Dynamic: license-file
Dynamic: requires-python
